tc_admin-5.1.1.dist-info/licenses/LICENSE
tcadmin/__init__.py
tcadmin/appconfig.py
tcadmin/apply.py
tcadmin/boot.py
tcadmin/callbacks.py
tcadmin/check.py
tcadmin/constants.py
tcadmin/diff.py
tcadmin/generate.py
tcadmin/main.py
tcadmin/options.py
tcadmin/output.py
tcadmin/update.py
tcadmin/current/__init__.py
tcadmin/current/clients.py
tcadmin/current/hooks.py
tcadmin/current/roles.py
tcadmin/current/secrets.py
tcadmin/current/worker_pools.py
tcadmin/resources/__init__.py
tcadmin/resources/client.py
tcadmin/resources/hook.py
tcadmin/resources/resources.py
tcadmin/resources/role.py
tcadmin/resources/secret.py
tcadmin/resources/util.py
tcadmin/resources/worker_pool.py
tcadmin/util/__init__.py
tcadmin/util/ansi.py
tcadmin/util/config.py
tcadmin/util/json.py
tcadmin/util/matchlist.py
tcadmin/util/root_url.py
tcadmin/util/scopes.py
tcadmin/util/sessions.py
tcadmin/util/taskcluster.py
tc_admin-5.1.1.dist-info/METADATA
tc_admin-5.1.1.dist-info/WHEEL
tc_admin-5.1.1.dist-info/entry_points.txt
tc_admin-5.1.1.dist-info/top_level.txt
tc_admin-5.1.1.dist-info/RECORD
