Metadata-Version: 2.4
Name: tc-admin
Version: 5.1.1
Summary: Administration of Taskcluster runtime configuration
Home-page: https://github.com/taskcluster/tc-admin
Author: Dustin Mitchell
Author-email: dustin@mozilla.com
Classifier: Programming Language :: Python :: 3.9
Classifier: Programming Language :: Python :: 3.10
Classifier: Programming Language :: Python :: 3.11
Classifier: Programming Language :: Python :: 3.12
Classifier: Programming Language :: Python :: 3.13
Classifier: Programming Language :: Python :: 3.14
License-File: LICENSE
Requires-Dist: taskcluster
Requires-Dist: click<8.4,>=8.0.0
Requires-Dist: blessings~=1.7
Requires-Dist: attrs<25.5,>=21.4.0
Requires-Dist: sortedcontainers~=2.4.0
Requires-Dist: aiohttp<3.14,>=3.8.0
Requires-Dist: pytest<8.5,>=7.0.0
Requires-Dist: pyyaml~=6.0
Dynamic: author
Dynamic: author-email
Dynamic: classifier
Dynamic: description
Dynamic: description-content-type
Dynamic: home-page
Dynamic: license-file
Dynamic: requires-dist
Dynamic: summary
